odoo10_addon_account_cash_discount_payment-10.0.1.0.0.99.dev11-py2.7-nspkg.pth
odoo/addons/account_cash_discount_payment/README.rst
odoo/addons/account_cash_discount_payment/__init__.py
odoo/addons/account_cash_discount_payment/__manifest__.py
odoo/addons/account_cash_discount_payment/i18n/account_cash_discount_payment.pot
odoo/addons/account_cash_discount_payment/i18n/fr.po
odoo/addons/account_cash_discount_payment/models/__init__.py
odoo/addons/account_cash_discount_payment/models/account_invoice.py
odoo/addons/account_cash_discount_payment/models/account_move_line.py
odoo/addons/account_cash_discount_payment/models/account_payment_line.py
odoo/addons/account_cash_discount_payment/static/description/icon.png
odoo/addons/account_cash_discount_payment/tests/__init__.py
odoo/addons/account_cash_discount_payment/tests/common.py
odoo/addons/account_cash_discount_payment/tests/test_account_cash_discount_payment.py
odoo/addons/account_cash_discount_payment/views/account_move_line.xml
odoo/addons/account_cash_discount_payment/views/account_payment_line.xml
odoo/addons/account_cash_discount_payment/wizards/__init__.py
odoo/addons/account_cash_discount_payment/wizards/account_payment_line_create.py
odoo/addons/account_cash_discount_payment/wizards/account_payment_line_create.xml
odoo10_addon_account_cash_discount_payment-10.0.1.0.0.99.dev11.dist-info/METADATA
odoo10_addon_account_cash_discount_payment-10.0.1.0.0.99.dev11.dist-info/RECORD
odoo10_addon_account_cash_discount_payment-10.0.1.0.0.99.dev11.dist-info/WHEEL
odoo10_addon_account_cash_discount_payment-10.0.1.0.0.99.dev11.dist-info/namespace_packages.txt
odoo10_addon_account_cash_discount_payment-10.0.1.0.0.99.dev11.dist-info/top_level.txt
